PyYandexLMS/__init__.py
PyYandexLMS/asynchronous/__init__.py
PyYandexLMS/asynchronous/client.py
PyYandexLMS/errors.py
PyYandexLMS/models/__init__.py
PyYandexLMS/models/base/__init__.py
PyYandexLMS/models/base/lesson.py
PyYandexLMS/models/base/main.py
PyYandexLMS/models/base/material.py
PyYandexLMS/models/base/profile.py
PyYandexLMS/models/base/solution.py
PyYandexLMS/models/base/task.py
PyYandexLMS/models/comment.py
PyYandexLMS/models/course.py
PyYandexLMS/models/file.py
PyYandexLMS/models/group.py
PyYandexLMS/models/input.py
PyYandexLMS/models/invite.py
PyYandexLMS/models/layout.py
PyYandexLMS/models/lesson.py
PyYandexLMS/models/materials.py
PyYandexLMS/models/notification.py
PyYandexLMS/models/placement.py
PyYandexLMS/models/problem.py
PyYandexLMS/models/profile.py
PyYandexLMS/models/progress.py
PyYandexLMS/models/resource.py
PyYandexLMS/models/schedule_plan.py
PyYandexLMS/models/solution.py
PyYandexLMS/models/status.py
PyYandexLMS/models/submission.py
PyYandexLMS/models/tag.py
PyYandexLMS/models/task.py
PyYandexLMS/models/user.py
PyYandexLMS/models/variant.py
PyYandexLMS/models/verdict.py
PyYandexLMS/synchronous/__init__.py
PyYandexLMS/synchronous/client.py
PyYandexLMS/utils/__init__.py
PyYandexLMS/utils/link_generator.py
PyYandexLMS/utils/validation.py
pyyandexlms-0.3.8.dist-info/WHEEL
pyyandexlms-0.3.8.dist-info/METADATA
pyyandexlms-0.3.8.dist-info/RECORD
